umlextensions/ErrorFormatter.py
umlextensions/ExtensionsFacade.py
umlextensions/ExtensionsManager.py
umlextensions/ExtensionsPreferences.py
umlextensions/ExtensionsPubSub.py
umlextensions/ExtensionsTypes.py
umlextensions/IExtensionsFacade.py
umlextensions/StackTraceFormatter.py
umlextensions/__init__.py
umlextensions/_version.py
umlextensions/py.typed
umlextensions/extensiontypes/BaseExtension.py
umlextensions/extensiontypes/BaseFormat.py
umlextensions/extensiontypes/BaseRequestResponse.py
umlextensions/extensiontypes/ExtensionDataTypes.py
umlextensions/extensiontypes/InvalidPluginExtensionException.py
umlextensions/extensiontypes/InvalidPluginNameException.py
umlextensions/extensiontypes/__init__.py
umlextensions/extensiontypes/py.typed
umlextensions/input/BaseInputExtension.py
umlextensions/input/ImportDirectoryResponse.py
umlextensions/input/InputFormat.py
umlextensions/input/InputPython.py
umlextensions/input/__init__.py
umlextensions/input/py.typed
umlextensions/input/python/DlgSelectMultiplePackages.py
umlextensions/input/python/DlgShapeLayoutParameters.py
umlextensions/input/python/NamedSlider.py
umlextensions/input/python/PythonParseException.py
umlextensions/input/python/PythonToUmlShapes.py
umlextensions/input/python/__init__.py
umlextensions/input/python/py.typed
umlextensions/input/python/pythonpegparser/PythonLexer.py
umlextensions/input/python/pythonpegparser/PythonLexerBase.py
umlextensions/input/python/pythonpegparser/PythonParser.py
umlextensions/input/python/pythonpegparser/PythonParserVisitor.py
umlextensions/input/python/visitor/BaseVisitor.py
umlextensions/input/python/visitor/ParentsDictionaryHandler.py
umlextensions/input/python/visitor/ParserTypes.py
umlextensions/input/python/visitor/PythonPegParserClassVisitor.py
umlextensions/input/python/visitor/PythonPegParserVisitor.py
umlextensions/input/python/visitor/__init__.py
umlextensions/input/python/visitor/py.typed
umlextensions/output/BaseOutputExtension.py
umlextensions/output/__init__.py
umlextensions-0.1.1.dist-info/licenses/LICENSE
umlextensions-0.1.1.dist-info/METADATA
umlextensions-0.1.1.dist-info/WHEEL
umlextensions-0.1.1.dist-info/entry_points.txt
umlextensions-0.1.1.dist-info/top_level.txt
umlextensions-0.1.1.dist-info/RECORD
