Metadata-Version: 2.4
Name: umlextensions
Version: 0.1.1
Summary: Plugins for umldiagrammer
Author-email: "Humberto A. Sanchez II" <Humberto.A.Sanchez.II@gmail.com>
Maintainer-email: "Humberto A. Sanchez II" <Humberto.A.Sanchez.II@gmail.com>
License-Expression: AGPL-1.0-or-later
Project-URL: Repository, https://github.com/hasii2011/umlextensions
Keywords: umldiagrammer,graphical,uml shapes,python
Classifier: Programming Language :: Python
Classifier: Intended Audience :: Developers
Classifier: Operating System :: MacOS :: MacOS X
Classifier: Topic :: Software Development :: Libraries :: Python Modules
License-File: LICENSE
Requires-Dist: wxPython~=4.2.3
Requires-Dist: codeallybasic>=1.30.0
Requires-Dist: codeallyadvanced>=2.2.0
Requires-Dist: pyutmodelv2>=2.2.6
Requires-Dist: umlshapes>=0.9.317
Requires-Dist: umlio>=0.4.8
Requires-Dist: antlr4-python3-runtime==4.13.2
Requires-Dist: Pypubsub==4.0.3
Provides-Extra: test
Requires-Dist: mypy==1.17.1; extra == "test"
Requires-Dist: mypy-extensions==1.1.0; extra == "test"
Requires-Dist: types-Deprecated==1.2.15.20250304; extra == "test"
Requires-Dist: html-testRunner~=1.2.1; extra == "test"
Provides-Extra: deploy
Requires-Dist: wheel==0.45.1; extra == "deploy"
Requires-Dist: setuptools==80.9.0; extra == "deploy"
Requires-Dist: twine==6.1.0; extra == "deploy"
Requires-Dist: build==1.3.0; extra == "deploy"
Requires-Dist: pkginfo==1.12.1.2; extra == "deploy"
Dynamic: license-file
